rous/__init__.py
rous/rous.py
rous-0.1.0.dist-info/LICENSE
rous-0.1.0.dist-info/METADATA
rous-0.1.0.dist-info/WHEEL
rous-0.1.0.dist-info/top_level.txt
rous-0.1.0.dist-info/RECORD
